autolr/__init__.py
autolr/autolr.py
autolr/preprocessing.py
autolr/requirements.txt
autolr-0.0.2.dist-info/LICENSE
autolr-0.0.2.dist-info/METADATA
autolr-0.0.2.dist-info/WHEEL
autolr-0.0.2.dist-info/top_level.txt
autolr-0.0.2.dist-info/RECORD
