Metadata-Version: 2.1
Name: autolr
Version: 0.0.2
Summary: A simple package for automatic logistic regression
Author: Ayush Pratap Singh
Author-email: ayushpsingh113@gmail.com
Project-URL: Source, https://github.com/ayushpratap113/autolr
Classifier: Programming Language :: Python :: 3.9
Classifier: License :: OSI Approved :: MIT License
Classifier: Intended Audience :: Information Technology
Classifier: Operating System :: OS Independent
Classifier: Topic :: Scientific/Engineering :: Artificial Intelligence
Requires-Python: >=3.8
License-File: LICENSE
Requires-Dist: numpy >=1.21.2
Requires-Dist: pandas >=1.4.2
Requires-Dist: scikit-learn
Requires-Dist: imbalanced-learn >=0.11.0
